{
  "fetched_at": "2026-05-26T10:35:21Z",
  "summary": {
    "difficulty": 0.0004827382495757118,
    "difficultyHybrid": "",
    "supply": 5927521,
    "hashrate": "41428.2637",
    "lastPrice": 0.00051275,
    "lastUSDPrice": 0.00051275,
    "connections": 68,
    "blockcount": 123859,
    "masternodeCountOnline": 92,
    "masternodeCountOffline": 2
  },
  "current_price": {
    "last_price_btc": null,
    "last_price_usd": 0.00051275
  },
  "release": {
    "tag_name": "v0.3.1",
    "name": "Smartiecoin Core v0.3.1",
    "html_url": "https://github.com/SmartiesCoin/Smartiecoin/releases/tag/v0.3.1",
    "published_at": "2026-05-10T17:53:45Z"
  }
}
