{
  "fetched_at": "2026-04-13T04:37:40Z",
  "summary": {
    "difficulty": 0.003540111650049092,
    "difficultyHybrid": "",
    "supply": 3047073,
    "hashrate": "166375.4917",
    "lastPrice": 0.0028937125,
    "lastUSDPrice": 0.0028937125,
    "connections": 64,
    "blockcount": 64649,
    "masternodeCountOnline": 30,
    "masternodeCountOffline": 8
  },
  "current_price": {
    "last_price_btc": null,
    "last_price_usd": 0.0028937125
  },
  "release": {
    "tag_name": "v0.1.9",
    "name": "v0.1.9",
    "html_url": "https://github.com/SmartiesCoin/Smartiecoin/releases/tag/v0.1.9",
    "published_at": "2026-04-02T19:50:49Z"
  }
}
