{
  "fetched_at": "2026-06-10T00:00:46Z",
  "summary": {
    "difficulty": 0.002994001306971685,
    "difficultyHybrid": "",
    "supply": 6933404,
    "hashrate": "160196.6274",
    "lastPrice": 0.01,
    "lastUSDPrice": 0.01,
    "connections": 127,
    "blockcount": 143810,
    "masternodeCountOnline": 106,
    "masternodeCountOffline": 2
  },
  "current_price": {
    "last_price_btc": null,
    "last_price_usd": 0.01
  },
  "masternode_stats": {
    "counts": {
      "total": 109,
      "online": 107,
      "offline": 2,
      "pose_banned": 2
    },
    "queue_depth": 107,
    "locked": {
      "regular_nodes": 48,
      "evo_nodes": 60,
      "total_nodes": 108,
      "regular_smt": 720000,
      "evo_smt": 4500000,
      "total_smt": 5220000,
      "source": "protx_list_registered",
      "supply_smt": 6933404,
      "percent_of_supply": 75.28769418311698
    },
    "estimation": {
      "block_time_seconds": 60,
      "payments_per_block": 1,
      "lookback_blocks": 2880,
      "regular_collateral": 15000,
      "evo_collateral": 75000,
      "evo_weight": 5
    },
    "rewards": {
      "network_reward_per_block": 34.175066029583334,
      "network_reward_per_day": 49212.0950826,
      "regular_reward_per_day": 459.9261222672897,
      "evo_reward_per_day": 2299.6306113364485,
      "source": "latest_chart_day",
      "chart_reference_day": "2026-06-09",
      "chart_reference_payments": 1367
    },
    "roi": {
      "regular_annual_percent": 1119.1535641837384,
      "evo_annual_percent": 1119.1535641837384
    },
    "lookback": {
      "since_block": 140930,
      "current_block": 143810,
      "payment_count": 2880,
      "total_reward": 103680.14839573
    }
  },
  "release": {
    "tag_name": "v0.3.7",
    "name": "Smartiecoin Core v0.3.7",
    "html_url": "https://github.com/SmartiesCoin/Smartiecoin/releases/tag/v0.3.7",
    "published_at": "2026-06-06T10:01:06Z"
  }
}
