{
  "fetched_at": "2026-04-06T04:49:24Z",
  "summary": {
    "difficulty": 0.00232206534309946,
    "difficultyHybrid": "",
    "supply": 2616064,
    "hashrate": "208248.3773",
    "lastPrice": 0.0028937125,
    "lastUSDPrice": 0.0028937125,
    "connections": 75,
    "blockcount": 55071,
    "masternodeCountOnline": 51,
    "masternodeCountOffline": 3
  },
  "current_price": {
    "last_price_btc": null,
    "last_price_usd": 0.0028937125
  },
  "release": {
    "tag_name": "v0.1.9",
    "name": "v0.1.9",
    "html_url": "https://github.com/SmartiesCoin/Smartiecoin/releases/tag/v0.1.9",
    "published_at": "2026-04-02T19:50:49Z"
  }
}
