{
  "fetched_at": "2026-04-08T11:52:49Z",
  "summary": {
    "difficulty": 0.00227023371126798,
    "difficultyHybrid": "",
    "supply": 2757678,
    "hashrate": "194181.0759",
    "lastPrice": 0.0028937125,
    "lastUSDPrice": 0.0028937125,
    "connections": 75,
    "blockcount": 58215,
    "masternodeCountOnline": 50,
    "masternodeCountOffline": 3
  },
  "current_price": {
    "last_price_btc": null,
    "last_price_usd": 0.0028937125
  },
  "release": {
    "tag_name": "v0.1.9",
    "name": "v0.1.9",
    "html_url": "https://github.com/SmartiesCoin/Smartiecoin/releases/tag/v0.1.9",
    "published_at": "2026-04-02T19:50:49Z"
  }
}
