{
  "fetched_at": "2026-04-22T04:16:09Z",
  "summary": {
    "difficulty": 0.002843263736172198,
    "difficultyHybrid": "",
    "supply": 3708437,
    "hashrate": "161528.7523",
    "lastPrice": 0.0028937125,
    "lastUSDPrice": 0.0028937125,
    "connections": 71,
    "blockcount": 76944,
    "masternodeCountOnline": 46,
    "masternodeCountOffline": 5
  },
  "current_price": {
    "last_price_btc": null,
    "last_price_usd": 0.0028937125
  },
  "release": {
    "tag_name": "v0.2.0",
    "name": "v0.2.0 — Violet/Orange UI Refresh",
    "html_url": "https://github.com/SmartiesCoin/Smartiecoin/releases/tag/v0.2.0",
    "published_at": "2026-04-17T18:15:30Z"
  }
}
