{
  "fetched_at": "2026-05-04T12:01:59Z",
  "summary": {
    "difficulty": 0.002996875402418609,
    "difficultyHybrid": "",
    "supply": 4468802,
    "hashrate": "186535.0305",
    "lastPrice": 0.00164118,
    "lastUSDPrice": 0.00164118,
    "connections": 84,
    "blockcount": 93842,
    "masternodeCountOnline": 71,
    "masternodeCountOffline": 3
  },
  "current_price": {
    "last_price_btc": null,
    "last_price_usd": 0.00164118
  },
  "release": {
    "tag_name": "v0.3.0",
    "name": "v0.3.0 — Reward Realloc (18/72/10)",
    "html_url": "https://github.com/SmartiesCoin/Smartiecoin/releases/tag/v0.3.0",
    "published_at": "2026-04-23T19:54:25Z"
  }
}
