{
  "fetched_at": "2026-05-23T01:30:35Z",
  "summary": {
    "difficulty": 0.001370436103779999,
    "difficultyHybrid": "",
    "supply": 5719621,
    "hashrate": "140980.3810",
    "lastPrice": 0.00061,
    "lastUSDPrice": 0.00061,
    "connections": 63,
    "blockcount": 119240,
    "masternodeCountOnline": 88,
    "masternodeCountOffline": 2
  },
  "current_price": {
    "last_price_btc": null,
    "last_price_usd": 0.00061
  },
  "release": {
    "tag_name": "v0.3.1",
    "name": "Smartiecoin Core v0.3.1",
    "html_url": "https://github.com/SmartiesCoin/Smartiecoin/releases/tag/v0.3.1",
    "published_at": "2026-05-10T17:53:45Z"
  }
}
