{
  "fetched_at": "2026-03-29T05:52:23Z",
  "summary": {
    "difficulty": 0.01003326662860654,
    "difficultyHybrid": "",
    "supply": 2128219,
    "hashrate": "606962.2945",
    "lastPrice": 0.0028937125,
    "lastUSDPrice": 0.0028937125,
    "connections": 53,
    "blockcount": 44227,
    "masternodeCountOnline": 48,
    "masternodeCountOffline": 0
  },
  "current_price": {
    "last_price_btc": null,
    "last_price_usd": 0.0028937125
  },
  "release": {
    "tag_name": "v0.1.8",
    "name": "Smartiecoin Core v0.1.8",
    "html_url": "https://github.com/SmartiesCoin/Smartiecoin/releases/tag/v0.1.8",
    "published_at": "2026-03-26T16:43:31Z"
  }
}
