{
  "fetched_at": "2026-05-01T18:15:48Z",
  "summary": {
    "difficulty": 0.002396563254788519,
    "difficultyHybrid": "",
    "supply": 4299422,
    "hashrate": "166086.8886",
    "lastPrice": 0.0028937125,
    "lastUSDPrice": 0.0028937125,
    "connections": 78,
    "blockcount": 90080,
    "masternodeCountOnline": 66,
    "masternodeCountOffline": 2
  },
  "current_price": {
    "last_price_btc": null,
    "last_price_usd": 0.0028937125
  },
  "release": {
    "tag_name": "v0.3.0",
    "name": "v0.3.0 — Reward Realloc (18/72/10)",
    "html_url": "https://github.com/SmartiesCoin/Smartiecoin/releases/tag/v0.3.0",
    "published_at": "2026-04-23T19:54:25Z"
  }
}
