{
  "fetched_at": "2026-05-04T22:59:13Z",
  "summary": {
    "difficulty": 0.003074511118250384,
    "difficultyHybrid": "",
    "supply": 4497062,
    "hashrate": "178074.8234",
    "lastPrice": 0.002,
    "lastUSDPrice": 0.002,
    "connections": 81,
    "blockcount": 94472,
    "masternodeCountOnline": 72,
    "masternodeCountOffline": 3
  },
  "current_price": {
    "last_price_btc": null,
    "last_price_usd": 0.002
  },
  "release": {
    "tag_name": "v0.3.0",
    "name": "v0.3.0 — Reward Realloc (18/72/10)",
    "html_url": "https://github.com/SmartiesCoin/Smartiecoin/releases/tag/v0.3.0",
    "published_at": "2026-04-23T19:54:25Z"
  }
}
