{
  "fetched_at": "2026-04-10T06:11:24Z",
  "summary": {
    "difficulty": 0.004016822170529255,
    "difficultyHybrid": "",
    "supply": 2866128,
    "hashrate": "305532.4331",
    "lastPrice": 0.0028937125,
    "lastUSDPrice": 0.0028937125,
    "connections": 59,
    "blockcount": 60627,
    "masternodeCountOnline": 32,
    "masternodeCountOffline": 5
  },
  "current_price": {
    "last_price_btc": null,
    "last_price_usd": 0.0028937125
  },
  "release": {
    "tag_name": "v0.1.9",
    "name": "v0.1.9",
    "html_url": "https://github.com/SmartiesCoin/Smartiecoin/releases/tag/v0.1.9",
    "published_at": "2026-04-02T19:50:49Z"
  }
}
