{
  "fetched_at": "2026-05-10T15:37:56Z",
  "summary": {
    "difficulty": 0.003077356963828483,
    "difficultyHybrid": "",
    "supply": 4847612,
    "hashrate": "167255.8204",
    "lastPrice": 0.00139636,
    "lastUSDPrice": 0.00139636,
    "connections": 89,
    "blockcount": 102263,
    "masternodeCountOnline": 76,
    "masternodeCountOffline": 6
  },
  "current_price": {
    "last_price_btc": null,
    "last_price_usd": 0.00139636
  },
  "release": {
    "tag_name": "v0.3.0",
    "name": "v0.3.0 — Reward Realloc (18/72/10)",
    "html_url": "https://github.com/SmartiesCoin/Smartiecoin/releases/tag/v0.3.0",
    "published_at": "2026-04-23T19:54:25Z"
  }
}
