{
  "fetched_at": "2026-06-30T14:45:08Z",
  "summary": {
    "difficulty": 0.001854399149208971,
    "difficultyHybrid": "",
    "supply": 8309143,
    "hashrate": "95805.8787",
    "lastPrice": 0.00070433,
    "lastUSDPrice": 0.00070433,
    "connections": 117,
    "blockcount": 171982,
    "masternodeCountOnline": 103,
    "masternodeCountOffline": 5
  },
  "current_price": {
    "last_price_btc": null,
    "last_price_usd": 0.00070433
  },
  "masternode_stats": null,
  "release": {
    "tag_name": "v0.4.1",
    "name": "Smartiecoin Core v0.4.1",
    "html_url": "https://github.com/SmartiesCoin/Smartiecoin/releases/tag/v0.4.1",
    "published_at": "2026-06-18T20:22:19Z"
  }
}
