{
  "fetched_at": "2026-07-11T04:27:54Z",
  "summary": {
    "difficulty": 0.001633273958771963,
    "difficultyHybrid": "",
    "supply": 8759593,
    "hashrate": "70500.9415",
    "lastPrice": 0.00073323,
    "lastUSDPrice": 0.00073323,
    "connections": 127,
    "blockcount": 179593,
    "masternodeCountOnline": 107,
    "masternodeCountOffline": 4
  },
  "current_price": {
    "last_price_btc": null,
    "last_price_usd": 0.00073323
  },
  "masternode_stats": {
    "counts": {
      "total": 111,
      "online": 107,
      "offline": 4,
      "pose_banned": 4
    },
    "queue_depth": 107,
    "locked": {
      "regular_nodes": 36,
      "evo_nodes": 75,
      "total_nodes": 111,
      "regular_smt": 540000,
      "evo_smt": 5625000,
      "total_smt": 6165000,
      "source": "protx_list_registered",
      "supply_smt": 8759593,
      "percent_of_supply": 70.37998226629935
    },
    "estimation": {
      "block_time_seconds": 60,
      "payments_per_block": 1,
      "lookback_blocks": 2880,
      "regular_collateral": 15000,
      "evo_collateral": 75000,
      "evo_weight": 5
    },
    "rewards": {
      "network_reward_per_block": 2.975000852041667,
      "network_reward_per_day": 4284.00122694,
      "regular_reward_per_day": 40.03739464429907,
      "evo_reward_per_day": 200.18697322149535,
      "source": "latest_chart_day",
      "chart_reference_day": "2026-07-11",
      "chart_reference_payments": 119
    },
    "roi": {
      "regular_annual_percent": 97.4243269677944,
      "evo_annual_percent": 97.4243269677944
    },
    "lookback": {
      "since_block": 176712,
      "current_block": 179592,
      "payment_count": 2870,
      "total_reward": 103320.07679173
    }
  },
  "release": {
    "tag_name": "v0.4.1",
    "name": "Smartiecoin Core v0.4.1",
    "html_url": "https://github.com/SmartiesCoin/Smartiecoin/releases/tag/v0.4.1",
    "published_at": "2026-06-18T20:22:19Z"
  }
}
