{
  "fetched_at": "2026-03-22T23:32:29Z",
  "summary": {
    "difficulty": 0.009357474813992791,
    "difficultyHybrid": "",
    "supply": 1742524,
    "hashrate": "656514.0829",
    "lastPrice": 0.0015692875,
    "lastUSDPrice": 0.0015692875,
    "connections": 60,
    "blockcount": 35657,
    "masternodeCountOnline": 39,
    "masternodeCountOffline": 0
  },
  "current_price": {
    "last_price_btc": null,
    "last_price_usd": 0.0015692875
  },
  "release": {
    "tag_name": "v0.1.5",
    "name": "Smartiecoin Core v0.1.5",
    "html_url": "https://github.com/SmartiesCoin/Smartiecoin/releases/tag/v0.1.5",
    "published_at": "2026-03-22T16:19:56Z"
  }
}
